josepy/__init__.py
josepy/b64.py
josepy/errors.py
josepy/interfaces.py
josepy/json_util.py
josepy/jwa.py
josepy/jwk.py
josepy/jws.py
josepy/magic_typing.py
josepy/py.typed
josepy/util.py
josepy-1.13.0.dist-info/LICENSE.txt
josepy-1.13.0.dist-info/METADATA
josepy-1.13.0.dist-info/WHEEL
josepy-1.13.0.dist-info/entry_points.txt
josepy-1.13.0.dist-info/top_level.txt
josepy-1.13.0.dist-info/RECORD
