Metadata-Version: 2.1
Name: josepy
Version: 1.13.0
Summary: JOSE protocol implementation in Python
Home-page: https://github.com/certbot/josepy
Author: Certbot Project
Author-email: client-dev@letsencrypt.org
License: Apache License 2.0
Platform: UNKNOWN
Classifier: Development Status :: 3 - Alpha
Classifier: Intended Audience :: Developers
Classifier: License :: OSI Approved :: Apache Software License
Classifier: Programming Language :: Python
Classifier: Programming Language :: Python :: 3
Classifier: Programming Language :: Python :: 3.6
Classifier: Programming Language :: Python :: 3.7
Classifier: Programming Language :: Python :: 3.8
Classifier: Programming Language :: Python :: 3.9
Classifier: Programming Language :: Python :: 3.10
Classifier: Topic :: Internet :: WWW/HTTP
Classifier: Topic :: Security
Requires-Python: >=3.6
Provides-Extra: dev
Provides-Extra: docs
Provides-Extra: tests
License-File: LICENSE.txt
